uipath/core/__init__.py
uipath/core/py.typed
uipath/core/chat/__init__.py
uipath/core/chat/async_stream.py
uipath/core/chat/citation.py
uipath/core/chat/content.py
uipath/core/chat/conversation.py
uipath/core/chat/error.py
uipath/core/chat/event.py
uipath/core/chat/exchange.py
uipath/core/chat/interrupt.py
uipath/core/chat/message.py
uipath/core/chat/meta.py
uipath/core/chat/tool.py
uipath/core/errors/__init__.py
uipath/core/errors/errors.py
uipath/core/guardrails/__init__.py
uipath/core/guardrails/_deterministic_guardrails_service.py
uipath/core/guardrails/_evaluators.py
uipath/core/guardrails/guardrails.py
uipath/core/tracing/__init__.py
uipath/core/tracing/_utils.py
uipath/core/tracing/decorators.py
uipath/core/tracing/exporters.py
uipath/core/tracing/processors.py
uipath/core/tracing/span_utils.py
uipath/core/tracing/trace_manager.py
uipath_core-0.1.6.dist-info/METADATA
uipath_core-0.1.6.dist-info/WHEEL
uipath_core-0.1.6.dist-info/licenses/LICENSE
uipath_core-0.1.6.dist-info/RECORD
